setup.py
random_proxy/__init__.py
random_proxy/proxy.py
random_proxy.egg-info/PKG-INFO
random_proxy.egg-info/SOURCES.txt
random_proxy.egg-info/dependency_links.txt
random_proxy.egg-info/top_level.txt