Metadata-Version: 1.0
Name: random-proxy
Version: 0.4
Summary: Generate a random proxy and return a tuple containes IP and Port.
Home-page: https://github.com/kuingsamlee/weiboCommentCrawl/blob/master/random_proxy.py
Author: kuing
Author-email: samleeforme@gmail.com
License: MIT
Keywords: spider proxy generator.
Platform: all
